mystepupmodule/__init__.py
mystepupmodule/title.py
mystepupmodule-1.0.dist-info/METADATA
mystepupmodule-1.0.dist-info/WHEEL
mystepupmodule-1.0.dist-info/top_level.txt
mystepupmodule-1.0.dist-info/RECORD
