Metadata-Version: 2.1
Name: mystepupmodule
Version: 1.0
Summary: My third Python library
Home-page: UNKNOWN
Author: Stepup
License: MIT
Platform: UNKNOWN
